conda_project/__init__.py
conda_project/__main__.py
conda_project/_conda_lock.py
conda_project/_version.py
conda_project/conda.py
conda_project/exceptions.py
conda_project/project.py
conda_project/project_file.py
conda_project/utils.py
conda_project/cli/__init__.py
conda_project/cli/commands.py
conda_project/cli/main.py
conda_project-0.5.4.dist-info/METADATA
conda_project-0.5.4.dist-info/WHEEL
conda_project-0.5.4.dist-info/entry_points.txt
conda_project-0.5.4.dist-info/licenses/LICENSE
conda_project-0.5.4.dist-info/RECORD
