Metadata-Version: 2.4
Name: conda-project
Version: 0.5.4
Summary: Tool for encapsulating, running, and reproducing projects with conda environments
Project-URL: repository, https://github.com/conda-incubator/conda-project
Project-URL: homepage, https://github.com/conda-incubator/conda-project
Project-URL: documentation, https://conda-incubator.github.io/conda-project/user_guide.html
Project-URL: Issue Tracker, https://github.com/conda-incubator/conda-project/issues
Project-URL: Conda-Forge Feedstock, https://github.com/conda-forge/conda-project-feedstock
Project-URL: AnacondaRecipes Feedstock, https://github.com/AnacondaRecipes/conda-project-feedstock
Author-email: Albert DeFusco <adefusco@anaconda.com>, Matt Kramer <mkramer@anaconda.com>
License-Expression: BSD-3-Clause
License-File: LICENSE
Keywords: conda-project
Classifier: Development Status :: 3 - Alpha
Classifier: Intended Audience :: Developers
Classifier: License :: OSI Approved :: BSD License
Classifier: Operating System :: OS Independent
Classifier: Programming Language :: Python
Classifier: Programming Language :: Python :: 3 :: Only
Classifier: Programming Language :: Python :: 3.8
Classifier: Programming Language :: Python :: 3.9
Classifier: Programming Language :: Python :: 3.10
Classifier: Programming Language :: Python :: 3.11
Classifier: Programming Language :: Python :: 3.12
Classifier: Programming Language :: Python :: 3.13
Classifier: Programming Language :: Python :: Implementation :: CPython
Classifier: Topic :: Software Development :: Libraries :: Python Modules
Classifier: Topic :: System :: Archiving :: Packaging
Classifier: Topic :: Utilities
Requires-Python: >=3.8
Requires-Dist: conda-lock>=2.5.6
Requires-Dist: fsspec
Requires-Dist: libarchive-c
Requires-Dist: lockfile
Requires-Dist: pexpect
Requires-Dist: pydantic
Requires-Dist: python-dotenv
Requires-Dist: ruamel-yaml
Requires-Dist: setuptools
Requires-Dist: shellingham
Provides-Extra: dev
Requires-Dist: flake8; extra == 'dev'
Requires-Dist: mypy; extra == 'dev'
Requires-Dist: pylint; extra == 'dev'
Requires-Dist: pytest; extra == 'dev'
Requires-Dist: pytest-cov; extra == 'dev'
Requires-Dist: pytest-mock; extra == 'dev'
Provides-Extra: docs
Requires-Dist: conda-sphinx-theme>=0.1.1; extra == 'docs'
Requires-Dist: myst-parser>=0.18.0; extra == 'docs'
Requires-Dist: sphinx-autobuild>=2021.3.14; extra == 'docs'
Requires-Dist: sphinx-autodoc-typehints>=1.19.2; extra == 'docs'
Requires-Dist: sphinx>=5.1.1; extra == 'docs'
